{
  "tin_tuc": [
    {
      "title": "SpaceX có thể giúp Elon Musk sở hữu 1.000 tỷ USD",
      "summary": "Công ty hàng không vũ trụ SpaceX dự kiến làm IPO tuần tới, có thể giúp tài sản của Elon Musk, người giàu nhất thế giới, tăng cao.",
      "link": "https://vnexpress.net/spacex-co-the-giup-elon-musk-so-huu-1-000-ty-usd-5081537.html",
      "date": "Wed, 03 Jun 2026 15:42:39 +0700",
      "source": "Kinh doanh - VnExpress RSS"
    },
    {
      "title": "'Ông lớn' bất động sản TP HCM đề xuất giảm sở hữu nhà nước",
      "summary": "Becamex, tập đoàn phát triển bất động sản và hạ tầng hàng đầu phía Nam, kiến nghị UBND TP HCM giảm vốn nhà nước từ 95,44% xuống khoảng 65% trong 5 năm tới.",
      "link": "https://vnexpress.net/ong-lon-bat-dong-san-tp-hcm-de-xuat-giam-so-huu-nha-nuoc-5081585.html",
      "date": "Wed, 03 Jun 2026 15:35:29 +0700",
      "source": "Kinh doanh - VnExpress RSS"
    },
    {
      "title": "Các hãng xe đồng loạt công bố danh mục xe tương thích xăng E10",
      "summary": "Nhiều hãng ôtô xác nhận các mẫu xe tương thích với xăng E10, trong bối cảnh loại nhiên liệu này được bán đại trà từ 1/6.",
      "link": "https://vnexpress.net/cac-hang-xe-dong-loat-cong-bo-danh-muc-xe-tuong-thich-xang-e10-5081521.html",
      "date": "Wed, 03 Jun 2026 13:44:59 +0700",
      "source": "Kinh doanh - VnExpress RSS"
    },
    {
      "title": "Bitcoin giảm mạnh nhất 4 tháng qua",
      "summary": "Động thái bán ra của \"ông lớn\" Strategy dấy lên lo ngại về tiềm năng của tiền số, đẩy Bitcoin giảm hơn 6%, mức giảm mạnh nhất 4 tháng qua.",
      "link": "https://vnexpress.net/bitcoin-giam-manh-nhat-4-thang-qua-5081374.html",
      "date": "Wed, 03 Jun 2026 11:23:23 +0700",
      "source": "Kinh doanh - VnExpress RSS"
    },
    {
      "title": "Chính quyền ông Trump muốn áp thuế 25% với hàng Brazil",
      "summary": "Cáo buộc Brazil tham gia các hoạt động thương mại \"phi lý\", Văn phòng Đại diện Thương mại Mỹ đề xuất áp thuế 25% hàng nhập khẩu nước này.",
      "link": "https://vnexpress.net/chinh-quyen-ong-trump-muon-ap-thue-25-voi-hang-brazil-5081391.html",
      "date": "Wed, 03 Jun 2026 10:50:59 +0700",
      "source": "Kinh doanh - VnExpress RSS"
    },
    {
      "title": "Doanh nghiệp toàn cầu có thể mất 17 tỷ USD vì nhân viên xem World Cup",
      "summary": "Nghiên cứu mới cho thấy doanh nghiệp có thể chịu thiệt hại năng suất khi nhân viên khó tập trung, không đi làm đúng giờ trong mùa World Cup 2026.",
      "link": "https://vnexpress.net/doanh-nghiep-toan-cau-co-the-mat-17-ty-usd-vi-nhan-vien-xem-world-cup-5081396.html",
      "date": "Wed, 03 Jun 2026 10:43:50 +0700",
      "source": "Kinh doanh - VnExpress RSS"
    },
    {
      "title": "Liên Hợp Quốc kêu gọi thế giới chuẩn bị ứng phó với nắng nóng cực hạn do El Nino",
      "summary": "Cơ quan khí tượng Liên Hợp Quốc kêu gọi các nước chuẩn bị ứng phó với hiện tượng El Nino mạnh, có thể làm gia tăng thời tiết cực đoan những tháng tới.",
      "link": "https://vnexpress.net/lien-hop-quoc-keu-goi-the-gioi-chuan-bi-ung-pho-voi-nang-nong-cuc-han-do-el-nino-5081379.html",
      "date": "Wed, 03 Jun 2026 10:23:08 +0700",
      "source": "Kinh doanh - VnExpress RSS"
    },
    {
      "title": "Lãi suất tiết kiệm ngân hàng nào cao nhất?",
      "summary": "Lãi suất niêm yết đang phổ biến từ 6,5% trở lên trong khi khách gửi tiết kiệm vài trăm triệu đồng có thể thỏa thuận 8-8,5% tại một vài nhà băng nhỏ.",
      "link": "https://vnexpress.net/lai-suat-tiet-kiem-ngan-hang-nao-cao-nhat-5081143.html",
      "date": "Wed, 03 Jun 2026 06:00:00 +0700",
      "source": "Kinh doanh - VnExpress RSS"
    },
    {
      "title": "Gian lận thương mại thời AI: Cảnh báo cho doanh nghiệp xuất khẩu",
      "summary": "Trong thời buổi AI, với nhiều giấy tờ và nội dung số dễ bị làm giả, chuyên gia cảnh báo doanh nghiệp xuất khẩu Việt Nam cần cẩn thận và có biện pháp phòng vệ.",
      "link": "https://tuoitre.vn/gian-lan-thuong-mai-thoi-ai-canh-bao-cho-doanh-nghiep-xuat-khau-20260603153711238.htm",
      "date": "Wed, 03 Jun 2026 15:45:47 GMT+7",
      "source": "Tuổi Trẻ Online - Kinh doanh - RSS Feed"
    },
    {
      "title": "VN-Index giảm 7 phiên liên tiếp, cổ phiếu NVL tiếp tục bị bán mạnh",
      "summary": "VN-Index giảm 7,46 điểm trong phiên giao dịch ngày 3-6, nối dài chuỗi giảm lên 7 phiên liên tiếp. Áp lực từ nhóm bất động sản, đặc biệt là các cổ phiếu họ Vingroup, tiếp tục đè...",
      "link": "https://tuoitre.vn/vn-index-giam-7-phien-lien-tiep-co-phieu-nvl-tiep-tuc-bi-ban-manh-20260603152946918.htm",
      "date": "Wed, 03 Jun 2026 15:44:09 GMT+7",
      "source": "Tuổi Trẻ Online - Kinh doanh - RSS Feed"
    },
    {
      "title": "Cửa sáng nào cho nhà đầu tư cá nhân trước làn sóng IPO năm 2026?",
      "summary": "Chuyên gia khuyến nghị thay vì chạy theo cảm xúc hay tin đồn IPO, nhà đầu tư nên đánh giá kỹ tiềm năng tăng trưởng của doanh nghiệp và mức giá chào bán trước khi xuống tiền.",
      "link": "https://tuoitre.vn/cua-sang-nao-cho-nha-dau-tu-ca-nhan-truoc-lan-song-ipo-nam-2026-20260603141223133.htm",
      "date": "Wed, 03 Jun 2026 14:53:33 GMT+7",
      "source": "Tuổi Trẻ Online - Kinh doanh - RSS Feed"
    },
    {
      "title": "Thủ tướng Lê Minh Hưng: Tiếp cận trực diện các vấn đề, xây dựng các kịch bản điều hành chi tiết hơn",
      "summary": "Xây dựng các kịch bản điều hành vĩ mô chi tiết hơn nữa, chuẩn bị các giải pháp chính sách với liều lượng cụ thể khi xuất hiện biến động để có tấm đệm \"giảm sốc\" tác động từ bên...",
      "link": "https://tuoitre.vn/thu-tuong-le-minh-hung-tiep-can-truc-dien-cac-van-de-xay-dung-cac-kich-ban-dieu-hanh-chi-tiet-hon-20260603140028636.htm",
      "date": "Wed, 03 Jun 2026 14:14:00 GMT+7",
      "source": "Tuổi Trẻ Online - Kinh doanh - RSS Feed"
    }
  ],
  "chinh_sach": [
    {
      "title": "CSGT cảnh báo học viên không dùng 'mẹo' khi thi sa hình",
      "summary": "Cục Cảnh sát giao thông phát hiện một số video hướng dẫn thi sa hình bằng 'mẹo' trên mạng và cảnh báo học viên có thể bị đình chỉ sát hạch nếu thực hiện không đúng quy định.",
      "link": "https://vnexpress.net/csgt-canh-bao-hoc-vien-khong-dung-meo-khi-thi-sa-hinh-5081528.html",
      "date": "Wed, 03 Jun 2026 15:27:25 +0700",
      "source": "Thời sự - VnExpress RSS"
    },
    {
      "title": "Quét radar xuyên đất tìm mộ tập thể liệt sĩ từ 2 bức ảnh của cựu binh Mỹ",
      "summary": "Quân đội dự kiến dùng radar xuyên đất thăm dò dọc đường Trường Chinh, tìm hài cốt các liệt sĩ hy sinh trong Tết Mậu Thân 1968.",
      "link": "https://vnexpress.net/quet-radar-xuyen-dat-tim-mo-tap-the-liet-si-tu-2-buc-anh-cua-cuu-binh-my-5081522.html",
      "date": "Wed, 03 Jun 2026 15:00:09 +0700",
      "source": "Thời sự - VnExpress RSS"
    },
    {
      "title": "Đại hội Công đoàn sẽ thảo luận tăng năng suất, hỗ trợ tăng trưởng hai con số",
      "summary": "Thủ tướng sẽ thảo luận với đại biểu dự Đại hội Công đoàn Việt Nam lần thứ 14 về nâng cao năng suất lao động, góp phần thực hiện mục tiêu tăng trưởng kinh tế hai con số và cải...",
      "link": "https://vnexpress.net/dai-hoi-cong-doan-se-thao-luan-tang-nang-suat-ho-tro-tang-truong-hai-con-so-5081402.html",
      "date": "Wed, 03 Jun 2026 12:21:03 +0700",
      "source": "Thời sự - VnExpress RSS"
    },
    {
      "title": "Xe tải đâm đổ giá treo camera trạm cân, quốc lộ 5 ùn tắc 5 giờ",
      "summary": "Đang chạy trên quốc lộ 5 hướng Hải Phòng - Hà Nội, xe tải bất ngờ lao vào dải phân cách giữa, đâm đổ thiết bị trạm cân, gây ùn tắc kéo dài, sáng 3/6.",
      "link": "https://vnexpress.net/xe-tai-dam-do-gia-treo-camera-tram-can-quoc-lo-5-un-tac-5-gio-5081502.html",
      "date": "Wed, 03 Jun 2026 12:01:05 +0700",
      "source": "Thời sự - VnExpress RSS"
    },
    {
      "title": "Khu du lịch xây trái phép trên núi ở Phú Quốc bị tháo dỡ",
      "summary": "Khu du lịch The Peak Phú Quốc bị cưỡng chế tháo dỡ sau thời gian dài vi phạm về xây dựng, đất đai và lấn chiếm đất rừng phòng hộ, sáng 3/6.",
      "link": "https://vnexpress.net/khu-du-lich-xay-trai-phep-tren-nui-o-phu-quoc-bi-thao-do-5081401.html",
      "date": "Wed, 03 Jun 2026 10:18:45 +0700",
      "source": "Thời sự - VnExpress RSS"
    },
    {
      "title": "Xem xét mở rộng 15 đoạn cao tốc Bắc Nam lên 6 làn xe",
      "summary": "Bộ Xây dựng thống nhất đề xuất mở rộng 15 đoạn cao tốc Bắc Nam phía Đông từ Mai Sơn đến Cam Lộ và từ Quảng Ngãi đến Dầu Giây lên 6 làn xe bằng vốn đầu tư công.",
      "link": "https://vnexpress.net/xem-xet-mo-rong-15-doan-cao-toc-bac-nam-len-6-lan-xe-5081417.html",
      "date": "Wed, 03 Jun 2026 10:16:01 +0700",
      "source": "Thời sự - VnExpress RSS"
    },
    {
      "title": "Cửa biển vừa nạo vét xong đã bị bồi lấp",
      "summary": "Cửa biển Lý Hòa sau hai lần nạo vét với kinh phí 900 triệu đồng hiện đã bị cát bồi lấp chỉ sau vài đợt gió chướng, hàng trăm tàu cá mắc cạn.",
      "link": "https://vnexpress.net/cua-bien-vua-nao-vet-xong-da-bi-boi-lap-5081183.html",
      "date": "Wed, 03 Jun 2026 09:02:57 +0700",
      "source": "Thời sự - VnExpress RSS"
    },
    {
      "title": "Đề xuất nạo vét luồng hàng hải Soài Rạp để nâng cao năng lực khai thác cảng",
      "summary": "Tổng công ty Hàng hải Việt Nam đề xuất Bộ Xây dựng có kế hoạch và phương án nạo vét, nâng cấp tuyến luồng hàng hải Soài Rạp đạt độ sâu khoảng 12m nhằm nâng cao năng lực tiếp nhận...",
      "link": "https://tuoitre.vn/de-xuat-nao-vet-luong-hang-hai-soai-rap-de-nang-cao-nang-luc-khai-thac-cang-20260603155603176.htm",
      "date": "Wed, 03 Jun 2026 16:07:47 GMT+7",
      "source": "Tuổi Trẻ Online - Thời sự - RSS Feed"
    },
    {
      "title": "Sáp nhập thôn, tổ dân phố: Tránh đặt tên mới khô cứng hoặc chỉ theo số thứ tự",
      "summary": "Đại biểu Quốc hội Bùi Hoài Sơn cho rằng khi sáp nhập, cần ưu tiên phương án đặt tên thôn, tổ dân phố mới có tính kế thừa, tôn trọng lịch sử, tránh đặt tên khô cứng, vô cảm hoặc...",
      "link": "https://tuoitre.vn/sap-nhap-thon-to-dan-pho-tranh-dat-ten-moi-kho-cung-hoac-chi-theo-so-thu-tu-20260603154119934.htm",
      "date": "Wed, 03 Jun 2026 16:07:00 GMT+7",
      "source": "Tuổi Trẻ Online - Thời sự - RSS Feed"
    },
    {
      "title": "Một con cá dài gần 6m tung tăng bơi vào gần bờ biển ở Đà Nẵng",
      "summary": "Một con cá theo ngư dân là cá nhám voi (cá mập voi, tên ngư dân thường gọi là cá ông sứa) dài khoảng 6m bơi vào gần bờ biển ở Đà Nẵng được ngư dân quay lại.",
      "link": "https://tuoitre.vn/mot-con-ca-dai-gan-6m-tung-tang-boi-vao-gan-bo-bien-o-da-nang-20260603152420721.htm",
      "date": "Wed, 03 Jun 2026 16:05:39 GMT+7",
      "source": "Tuổi Trẻ Online - Thời sự - RSS Feed"
    },
    {
      "title": "Tổng Bí thư, Chủ tịch nước: Phát triển nhanh phải đi đôi với ổn định xã hội",
      "summary": "Tổng Bí thư, Chủ tịch nước Tô Lâm nhấn mạnh không đánh đổi trật tự kỷ cương, công bằng xã hội, môi trường và các giá trị văn hóa để lấy tăng trưởng kinh tế đơn thuần.",
      "link": "https://tuoitre.vn/tong-bi-thu-chu-tich-nuoc-khong-de-xa-hoi-giau-len-ve-vat-chat-nhung-ngheo-di-ve-van-hoa-dao-duc-20260603145247736.htm",
      "date": "Wed, 03 Jun 2026 15:31:00 GMT+7",
      "source": "Tuổi Trẻ Online - Thời sự - RSS Feed"
    },
    {
      "title": "Đại hội Công đoàn Việt Nam lần thứ XIV: Đề xuất giảm mức đóng công đoàn phí",
      "summary": "Ngày 3-6, tại phiên làm việc thứ nhất của Đại hội Công đoàn Việt Nam lần thứ XIV, dự thảo sửa đổi Điều lệ Công đoàn Việt Nam đã được trình bày với nhiều điểm mới mang tính đột...",
      "link": "https://tuoitre.vn/dai-hoi-cong-doan-viet-nam-lan-thu-xiv-de-xuat-giam-muc-dong-cong-doan-phi-20260603143704231.htm",
      "date": "Wed, 03 Jun 2026 15:11:51 GMT+7",
      "source": "Tuổi Trẻ Online - Thời sự - RSS Feed"
    }
  ],
  "last_updated": "2026-06-03T09:32:49.437755+00:00",
  "meta": {
    "tin_tuc_sources": [
      "VnExpress Kinh doanh",
      "Tuổi Trẻ Kinh doanh"
    ],
    "chinh_sach_sources": [
      "VnExpress Thời sự",
      "Tuổi Trẻ Thời sự",
      "VnExpress Pháp luật (một phần)"
    ]
  }
}