{
  "candles": [
    {
      "time": "2026-02-02",
      "open": 1824.1,
      "high": 1829.04,
      "low": 1777.85,
      "close": 1806.5
    },
    {
      "time": "2026-02-03",
      "open": 1807.09,
      "high": 1827.22,
      "low": 1805.22,
      "close": 1813.4
    },
    {
      "time": "2026-02-04",
      "open": 1813.87,
      "high": 1813.87,
      "low": 1780.71,
      "close": 1791.43
    },
    {
      "time": "2026-02-05",
      "open": 1789.14,
      "high": 1800.1,
      "low": 1782.18,
      "close": 1782.56
    },
    {
      "time": "2026-02-06",
      "open": 1768.77,
      "high": 1782.56,
      "low": 1755.49,
      "close": 1755.49
    },
    {
      "time": "2026-02-09",
      "open": 1769.76,
      "high": 1771.73,
      "low": 1749.87,
      "close": 1754.82
    },
    {
      "time": "2026-02-10",
      "open": 1755.83,
      "high": 1776.24,
      "low": 1741.37,
      "close": 1754.03
    },
    {
      "time": "2026-02-11",
      "open": 1768.18,
      "high": 1799.92,
      "low": 1754.03,
      "close": 1796.85
    },
    {
      "time": "2026-02-12",
      "open": 1809.01,
      "high": 1816.11,
      "low": 1796.85,
      "close": 1814.09
    },
    {
      "time": "2026-02-13",
      "open": 1818.07,
      "high": 1824.09,
      "low": 1792.91,
      "close": 1824.09
    },
    {
      "time": "2026-02-23",
      "open": 1833.9,
      "high": 1863.13,
      "low": 1824.09,
      "close": 1860.14
    },
    {
      "time": "2026-02-24",
      "open": 1862.18,
      "high": 1867.62,
      "low": 1849.6,
      "close": 1867.62
    },
    {
      "time": "2026-02-25",
      "open": 1869.49,
      "high": 1876.01,
      "low": 1857.16,
      "close": 1860.91
    },
    {
      "time": "2026-02-26",
      "open": 1861.32,
      "high": 1882.17,
      "low": 1859.04,
      "close": 1879.64
    },
    {
      "time": "2026-02-27",
      "open": 1883.12,
      "high": 1899.44,
      "low": 1868.91,
      "close": 1880.33
    },
    {
      "time": "2026-03-02",
      "open": 1876.01,
      "high": 1885.18,
      "low": 1844.25,
      "close": 1846.1
    },
    {
      "time": "2026-03-03",
      "open": 1854.28,
      "high": 1854.28,
      "low": 1808.55,
      "close": 1813.14
    },
    {
      "time": "2026-03-04",
      "open": 1803.54,
      "high": 1833.33,
      "low": 1766.86,
      "close": 1818.27
    },
    {
      "time": "2026-03-05",
      "open": 1837.34,
      "high": 1849.01,
      "low": 1808.07,
      "close": 1808.51
    },
    {
      "time": "2026-03-06",
      "open": 1801.08,
      "high": 1807.31,
      "low": 1767.84,
      "close": 1767.84
    },
    {
      "time": "2026-03-09",
      "open": 1757.73,
      "high": 1767.84,
      "low": 1651.68,
      "close": 1652.79
    },
    {
      "time": "2026-03-10",
      "open": 1664.52,
      "high": 1716.62,
      "low": 1651.29,
      "close": 1676.73
    },
    {
      "time": "2026-03-11",
      "open": 1675.87,
      "high": 1729.67,
      "low": 1675.17,
      "close": 1728.34
    },
    {
      "time": "2026-03-12",
      "open": 1716.62,
      "high": 1728.34,
      "low": 1701.59,
      "close": 1709.61
    },
    {
      "time": "2026-03-13",
      "open": 1697.72,
      "high": 1716.75,
      "low": 1688.67,
      "close": 1696.24
    },
    {
      "time": "2026-03-16",
      "open": 1701.06,
      "high": 1707.0,
      "low": 1680.7,
      "close": 1693.21
    },
    {
      "time": "2026-03-17",
      "open": 1709.38,
      "high": 1732.31,
      "low": 1693.21,
      "close": 1710.29
    },
    {
      "time": "2026-03-18",
      "open": 1718.3,
      "high": 1742.87,
      "low": 1706.53,
      "close": 1713.83
    },
    {
      "time": "2026-03-19",
      "open": 1700.77,
      "high": 1713.83,
      "low": 1685.9,
      "close": 1699.13
    },
    {
      "time": "2026-03-20",
      "open": 1698.62,
      "high": 1699.13,
      "low": 1647.16,
      "close": 1647.81
    },
    {
      "time": "2026-03-23",
      "open": 1630.11,
      "high": 1647.81,
      "low": 1586.44,
      "close": 1591.17
    },
    {
      "time": "2026-03-24",
      "open": 1626.34,
      "high": 1630.63,
      "low": 1591.17,
      "close": 1614.77
    },
    {
      "time": "2026-03-25",
      "open": 1634.15,
      "high": 1658.77,
      "low": 1614.77,
      "close": 1658.19
    },
    {
      "time": "2026-03-26",
      "open": 1661.53,
      "high": 1661.6,
      "low": 1634.55,
      "close": 1644.63
    },
    {
      "time": "2026-03-27",
      "open": 1643.89,
      "high": 1673.31,
      "low": 1640.31,
      "close": 1672.8
    },
    {
      "time": "2026-03-30",
      "open": 1646.08,
      "high": 1672.8,
      "low": 1637.58,
      "close": 1662.54
    },
    {
      "time": "2026-03-31",
      "open": 1669.57,
      "high": 1677.83,
      "low": 1662.54,
      "close": 1674.49
    },
    {
      "time": "2026-04-01",
      "open": 1713.92,
      "high": 1715.21,
      "low": 1700.18,
      "close": 1702.93
    },
    {
      "time": "2026-04-02",
      "open": 1706.15,
      "high": 1706.15,
      "low": 1684.47,
      "close": 1694.82
    },
    {
      "time": "2026-04-03",
      "open": 1700.14,
      "high": 1713.95,
      "low": 1679.79,
      "close": 1684.04
    },
    {
      "time": "2026-04-06",
      "open": 1682.09,
      "high": 1693.03,
      "low": 1669.31,
      "close": 1674.99
    },
    {
      "time": "2026-04-07",
      "open": 1677.99,
      "high": 1690.31,
      "low": 1665.36,
      "close": 1677.54
    },
    {
      "time": "2026-04-08",
      "open": 1706.59,
      "high": 1756.55,
      "low": 1706.59,
      "close": 1756.55
    },
    {
      "time": "2026-04-09",
      "open": 1750.88,
      "high": 1756.55,
      "low": 1736.68,
      "close": 1736.68
    },
    {
      "time": "2026-04-10",
      "open": 1750.86,
      "high": 1762.84,
      "low": 1736.68,
      "close": 1750.0
    },
    {
      "time": "2026-04-13",
      "open": 1738.57,
      "high": 1765.67,
      "low": 1733.18,
      "close": 1758.96
    },
    {
      "time": "2026-04-14",
      "open": 1775.41,
      "high": 1784.43,
      "low": 1758.96,
      "close": 1775.65
    },
    {
      "time": "2026-04-15",
      "open": 1787.37,
      "high": 1801.66,
      "low": 1775.65,
      "close": 1800.65
    },
    {
      "time": "2026-04-16",
      "open": 1806.2,
      "high": 1824.03,
      "low": 1799.18,
      "close": 1819.83
    },
    {
      "time": "2026-04-17",
      "open": 1832.33,
      "high": 1846.19,
      "low": 1814.47,
      "close": 1817.17
    },
    {
      "time": "2026-04-20",
      "open": 1819.03,
      "high": 1837.11,
      "low": 1802.42,
      "close": 1837.11
    },
    {
      "time": "2026-04-21",
      "open": 1851.84,
      "high": 1866.1,
      "low": 1833.48,
      "close": 1833.48
    },
    {
      "time": "2026-04-22",
      "open": 1834.53,
      "high": 1861.34,
      "low": 1819.21,
      "close": 1857.3
    },
    {
      "time": "2026-04-23",
      "open": 1868.31,
      "high": 1888.99,
      "low": 1855.09,
      "close": 1870.36
    },
    {
      "time": "2026-04-24",
      "open": 1873.23,
      "high": 1881.93,
      "low": 1843.63,
      "close": 1853.29
    },
    {
      "time": "2026-04-28",
      "open": 1850.07,
      "high": 1887.69,
      "low": 1848.98,
      "close": 1875.84
    },
    {
      "time": "2026-04-29",
      "open": 1878.96,
      "high": 1881.18,
      "low": 1852.49,
      "close": 1854.1
    },
    {
      "time": "2026-05-04",
      "open": 1870.66,
      "high": 1876.8,
      "low": 1840.43,
      "close": 1854.06
    },
    {
      "time": "2026-05-05",
      "open": 1853.08,
      "high": 1875.97,
      "low": 1849.32,
      "close": 1874.85
    },
    {
      "time": "2026-05-06",
      "open": 1881.22,
      "high": 1892.0,
      "low": 1868.92,
      "close": 1891.2
    },
    {
      "time": "2026-05-07",
      "open": 1897.44,
      "high": 1924.95,
      "low": 1891.2,
      "close": 1909.01
    },
    {
      "time": "2026-05-08",
      "open": 1911.15,
      "high": 1921.81,
      "low": 1897.06,
      "close": 1915.37
    },
    {
      "time": "2026-05-11",
      "open": 1918.93,
      "high": 1927.06,
      "low": 1893.75,
      "close": 1895.5
    },
    {
      "time": "2026-05-12",
      "open": 1893.2,
      "high": 1906.64,
      "low": 1875.25,
      "close": 1901.1
    },
    {
      "time": "2026-05-13",
      "open": 1908.77,
      "high": 1908.77,
      "low": 1865.12,
      "close": 1898.37
    },
    {
      "time": "2026-05-14",
      "open": 1896.72,
      "high": 1927.7,
      "low": 1883.98,
      "close": 1925.46
    },
    {
      "time": "2026-05-15",
      "open": 1928.61,
      "high": 1930.58,
      "low": 1909.9,
      "close": 1921.6
    },
    {
      "time": "2026-05-18",
      "open": 1916.56,
      "high": 1932.62,
      "low": 1908.78,
      "close": 1927.94
    },
    {
      "time": "2026-05-19",
      "open": 1933.01,
      "high": 1933.11,
      "low": 1904.47,
      "close": 1912.93
    },
    {
      "time": "2026-05-20",
      "open": 1907.1,
      "high": 1919.39,
      "low": 1859.22,
      "close": 1913.23
    },
    {
      "time": "2026-05-21",
      "open": 1920.44,
      "high": 1923.21,
      "low": 1886.62,
      "close": 1896.89
    },
    {
      "time": "2026-05-22",
      "open": 1896.74,
      "high": 1896.74,
      "low": 1856.08,
      "close": 1877.13
    },
    {
      "time": "2026-05-25",
      "open": 1876.37,
      "high": 1891.26,
      "low": 1876.37,
      "close": 1886.03
    },
    {
      "time": "2026-05-26",
      "open": 1889.15,
      "high": 1889.15,
      "low": 1876.32,
      "close": 1884.18
    },
    {
      "time": "2026-05-27",
      "open": 1889.87,
      "high": 1889.87,
      "low": 1863.18,
      "close": 1874.43
    },
    {
      "time": "2026-05-28",
      "open": 1869.7,
      "high": 1882.66,
      "low": 1857.25,
      "close": 1863.67
    },
    {
      "time": "2026-05-29",
      "open": 1864.42,
      "high": 1873.17,
      "low": 1851.04,
      "close": 1863.49
    }
  ]
}